Prompt_Framework/Prompt_Framework.py
Prompt_Framework/__init__.py
prompt_framework-1.0.0.dist-info/licenses/LICENSE
tests/__init__.py
tests/test_prompt_framework.py
prompt_framework-1.0.0.dist-info/METADATA
prompt_framework-1.0.0.dist-info/WHEEL
prompt_framework-1.0.0.dist-info/top_level.txt
prompt_framework-1.0.0.dist-info/RECORD
