Metadata-Version: 2.4
Name: Prompt_Framework
Version: 1.0.0
Summary: Prompt_Framework is a Python package that provides a set of flexible frameworks for prompt engineering. It allows seamless interchangability between various frameworks
Home-page: https://github.com/Subhagatoadak/Prompt_Framework
Author: Subhagato Adak
Author-email: subhagato.adak@gmail.com
Classifier: Programming Language :: Python :: 3
Classifier: License :: OSI Approved :: MIT License
Classifier: Operating System :: OS Independent
Requires-Python: >=3.7
License-File: LICENSE
Dynamic: author
Dynamic: author-email
Dynamic: classifier
Dynamic: description
Dynamic: description-content-type
Dynamic: home-page
Dynamic: license-file
Dynamic: requires-python
Dynamic: summary
